<colors>
	<!-- All others -->
	<color name="black">FF000000</color>
	<color name="white">FFFFFFFF</color>
	<color name="brightred">FFC80000</color>
	<color name="grey">FFC0C2C2</color>
	<color name="blue">FF7ACAFE</color>
	<color name="red">FFCE4421</color>
	<color name="midgrey">FF686868</color>
	<color name="bluegrey">ffC6C6C8</color>
	<color name="darkgrey">FF2C2C2C</color>
	<color name="darkgrey2">FF666769</color>
	<color name="yellow">FFFFD95C</color>
	<color name="pinkyred">FFFF6666</color>
	<!-- Home Labels -->
	<color name="homelabelbig">FFFFFFFF</color>
	<color name="homelabelsmall">FF62BEFE</color>
	<!-- List, Guide view -->
	<color name="greyblue">FF677173</color>
	<color name="listwhite">FFFFFFFF</color>
	<color name="guideblue">FF7ACAFE</color>
	<!-- List view -->
	<color name="greyblue">FF677173</color>
	<!-- Context menus, shutdown menes -->
	<color name="lightgrey">FFDDDDDD</color>
	<color name="darkgrey">FF2C2C2C</color>
	<!-- GuideButton -->
	<color name="guidebutton">FF44aef3</color> <!-- Green -->
	<!-- Other -->
	<color name="77white">77FFFFFF</color>
	<color name="aawhite">AAFFFFFF</color>
	<color name="bbwhite">BBFFFFFF</color>
	<color name="ddwhite">DDFFFFFF</color>
	<color name="eewhite">EEFFFFFF</color>
	<!-- Menus -->
	<color name="MediaBrowserGreen">FF42EE3A</color>
	<color name="MenuBlue">FF55B2FA</color>
	<color name="MenuGrey">CC484848</color>
	<color name="KeyboardGrey">99484848</color>
	<color name="SettingsBlue">FF55b4e7</color>
	<color name="DialogSelected">FF4ea1e7</color>
	<color name="SelectedRed">FFE10101</color>
	<color name="SelectedGreen">FF42EE3A</color>
	<color name="SelectedBlue">FF31D0FF</color>
	<color name="SelectedOrange">ffD6A51E</color>
	<color name="green">FF0A9903</color>
	
	<!-- WHITES AND BLACKS -->
	<color name="mod-black">ddeeeeee</color>
	<color name="mod-dimfanart">aaeeeeee</color>
	<!-- <color name="mod-infotags">ee404040</color> -->
	<color name="mod-infotags">ff000000</color>
	<color name="mod-infotags-li">cc404040</color>
	<color name="mod-infotags-l">aa404040</color>
	<color name="mod-infotags-vl">55404040</color>
	<!-- <color name="mod-infotags-a">cc777777</color> -->
	<color name="mod-infotags-a">ff000000</color>
	<color name="mod-infotags-d">ee181818</color>
	<color name="mod-infotags-alt">eeeeeeee</color>
	<color name="mod-infotags-alt2">eecccccc</color>
	<color name="mod-shadow">55ffffff</color>
	
	<!-- Focus Colours -->
	<color name="Blue Focus">ff0000ff</color>
	<color name="Green Focus">ff007949</color>
	<color name="Red Focus">ffee0000</color>
	<color name="Pink Focus">ffffc0cb</color>
	<color name="Purple Focus">ff3a0079</color>
	<color name="Lime Focus">ff32cd32</color>
	<color name="Grey Focus">ff404040</color>
	<color name="Orange Focus">fffdc700</color>
	<color name="Yellow Focus">ffffff00</color>
	<color name="Black Focus">ff000000</color>
	<color name="White Focus">ffffffff</color>
	<color name="Cyan Focus">ff00ffff</color>
	<color name="Magenta Focus">ffff00ff</color>
	<color name="Imdb Focus">fff3ce13</color>
	
	<!--background colours -->
	<color name="PrimaryBG">ff181818</color>
	<color name="SecondaryBG">FF555555</color>
	<color name="TertiaryBG">FF444444</color>
	<color name="QuaternaryBG">01000000</color>
	<color name="HomeBG">DD111111</color>
	<color name="HomeTileOverlay">88333333</color>
	<color name="HomeMenuOverlay">99333333</color>
	<color name="HomeTitleOverlay">AA222222</color>
	
	<!-- Default Tile Colours -->
	<color name="tilesearch">FF111111</color>
	<color name="tilehome">FF111111</color>
	<color name="tilelivetv">FF111111</color>
	<color name="tiletv">FF109909</color>
	<color name="tilemovies">FF2D89C2</color>
	<color name="tilemusic">FFFFD95C</color>
	<color name="tilechannels">FFFF6666</color>
	<color name="tilephotos">FF111111</color>
	<color name="tileapplications">FF111111</color>
	<color name="tileweather">FF111111</color>
	<color name="tilesettings">FF111111</color>
	
	
	<!--main colours-->
	<color name="PrimaryM">FFFFFFFF</color>
	<color name="PriSecondaryM">FF999999</color>
	<color name="SecondaryM">FF666666</color>
	<color name="SecondaryMT">CC5d5d5d</color>
	<color name="TertiaryM">FF222222</color>
	<color name="TertiaryMT">CC333333</color>
	<color name="QuaternaryM">FF494949</color>
	
	<!--text colours-->
	<color name="PrimaryT">FFFFFFFF</color>
	<color name="SecondaryT">FFAAAAAA</color>
	<color name="TertiaryT">FF999999</color>
	<color name="QuaternaryT">35FFFFFF</color>
	
	<!--osd colours-->
	<color name="PrimaryOSD">FFFFFFFF</color>
	<color name="SecondaryOSD">90FFFFFF</color>
	<color name="TertiaryOSD">30FFFFFF</color>
	
	<!--others-->
	<color name="Login">FFeaeaea</color>
	<color name="LoginT">FF939393</color>
	<color name="LoginT2">FF555555</color>
	<color name="Black">FF000000</color>
	<color name="Black95">BB000000</color>
	<color name="Blue">FFff0000</color>
	<color name="Red">FF006cff</color>
	<color name="White">FFFFFFFF</color>
	
</colors>